grpc_tunnel/__init__.py
grpc_tunnel/cli.py
grpc_tunnel/server.py
grpc_tunnel-1.0.0.dist-info/METADATA
grpc_tunnel-1.0.0.dist-info/WHEEL
grpc_tunnel-1.0.0.dist-info/entry_points.txt
grpc_tunnel-1.0.0.dist-info/licenses/LICENSE
grpc_tunnel-1.0.0.dist-info/RECORD
