Metadata-Version: 2.4
Name: grpc_tunnel
Version: 1.0.0
Summary: Expose your local gRPC server over the internet using ngrok.
Project-URL: Homepage, https://github.com/David3Emmanuel/grpc-tunnel
Project-URL: Issues, https://github.com/David3Emmanuel/grpc-tunnel/issues
Author-email: David Emmanuel <david3emmanuel@gmail.com>
License-Expression: Apache-2.0
License-File: LICENSE
Classifier: Operating System :: OS Independent
Classifier: Programming Language :: Python :: 3
Requires-Python: >=3.9
Requires-Dist: click
Requires-Dist: grpcio
Requires-Dist: grpcio-tools
Requires-Dist: pyngrok
